csptools/__init__.py
csptools/command/__init__.py
csptools/command/cli.py
csptools/common/__init__.py
csptools/common/nexus_config.py
csptools/common/utils.py
csptools/common/config/default.yaml
csptools/scripts/__init__.py
csptools/scripts/allTools.py
csptools/scripts/config.py
csptools/scripts/model_docker.py
csptools-0.1.2.dist-info/METADATA
csptools-0.1.2.dist-info/WHEEL
csptools-0.1.2.dist-info/entry_points.txt
csptools-0.1.2.dist-info/top_level.txt
csptools-0.1.2.dist-info/RECORD
